{
  "ClassName": "Actor",
  "ParentClassOverride": "WDOMPositionableEntityNode",
  "FourCC": "ACTR",
  "Fields": [
    {
      "Name": "Name",
      "Type": "FixedLengthString",
      "Length": 8,
      "Default": ""
    },
    {
      "Name": "Parameters",
      "Type": "Int",
      "Default": 0
    },
    {
      "Name": "Position",
      "Type": "Vector3",
      "Default": {
        "X": 0,
        "Y": 0,
        "Z": 0
      }
    },
    {
      "Name": "Auxillary Parameters 1",
      "Type": "Short"
    },
    {
      "Name": "Y Rotation",
      "Type": "YRotation"
    },
    {
      "Name": "Auxillary Parameters 2",
      "Type": "Short",
      "Default": 0
    },
    {
      "Name": "Enemy Number",
      "Type": "Short",
      "Default": 0
    }
  ]
}