{
  "ClassName": "obj_mkiek",
  "ParentClassOverride": "Actor",
  "ParameterFields": [
    {
      "Name": "Switch to Set",
      "ValueSource": "Parameters",
      "Mask": 0x000000FF,
      "Hidden": false,
      "Category": "Dissolving Wall",
      "ToolTip": "The switch to set when this wall is dissolved by light.",
      "DataType": "Integer"
    },
    {
      "Name": "Do Not Play Jingle",
      "ValueSource": "Parameters",
      "Mask": 0x00000100,
      "Hidden": false,
      "Category": "Dissolving Wall",
      "ToolTip": "If checked, dissolving this wall does not play the 'Puzzle Solved' jingle it normally would.",
      "DataType": "Boolean"
    }
  ]
}