{
  "ClassName": "tag_md_cb",
  "ParentClassOverride": "Actor",
  "Fields": [
    {
      "Name": "MessageID",
      "ValueSource": "Parameters",
      "Mask": 0x0000FFFF,
      "Shift": 0,
      "Hidden": false,
      "Category": "tag_md_cb"
    },
    {
      "Name": "Unknown_2",
      "ValueSource": "Parameters",
      "Mask": 0x00FF0000,
      "Shift": 16,
      "Hidden": false,
      "Category": "tag_md_cb"
    },
    {
      "Name": "Unknown_3",
      "ValueSource": "Parameters",
      "Mask": 0xFF000000,
      "Shift": 24,
      "Hidden": false,
      "Category": "tag_md_cb"
    },
    {
      "Name": "Unknown_4",
      "ValueSource": "AuxillaryParameters1",
      "Mask": 0x00FF,
      "Shift": 0,
      "Hidden": false,
      "Category": "tag_md_cb"
    }
  ]
}